[{"name":"Yes, And?","artist":"Ariana Grande","image":"https://charts-static.billboard.com/img/2024/01/ariana-grande-da0-yesandX-4fd-180x180.jpg","rank":1,"last_week_rank":null,"peak_rank":1,"weeks_on_chart":1},{"name":"Lovin On Me","artist":"Jack Harlow","image":"https://charts-static.billboard.com/img/2023/11/jackharlow-i43-lovinonme-y0w-180x180.jpg","rank":2,"last_week_rank":1,"peak_rank":1,"weeks_on_chart":10},{"name":"Cruel Summer","artist":"Taylor Swift","image":"https://charts-static.billboard.com/img/2019/08/taylor-swift-9sy-cruelsummer-i1p-180x180.jpg","rank":3,"last_week_rank":2,"peak_rank":1,"weeks_on_chart":37},{"name":"Greedy","artist":"Tate McRae","image":"https://charts-static.billboard.com/img/2023/09/tatemcrae-rxu-greedy-2h2-180x180.jpg","rank":4,"last_week_rank":3,"peak_rank":3,"weeks_on_chart":18},{"name":"Redrum","artist":"21 Savage","image":"https://charts-static.billboard.com/img/2016/08/21-savage-iy5-180x180.jpg","rank":5,"last_week_rank":null,"peak_rank":5,"weeks_on_chart":1},{"name":"I Remember Everything","artist":"Zach Bryan Featuring Kacey Musgraves","image":"https://charts-static.billboard.com/img/2023/09/zachbryan-de1-iremembereverything-to3-180x180.jpg","rank":6,"last_week_rank":4,"peak_rank":1,"weeks_on_chart":21},{"name":"Paint The Town Red","artist":"Doja Cat","image":"https://charts-static.billboard.com/img/2023/08/dojacat-cqv-paintthetownred-unh-180x180.jpg","rank":7,"last_week_rank":5,"peak_rank":1,"weeks_on_chart":24},{"name":"Lose Control","artist":"Teddy Swims","image":"https://charts-static.billboard.com/img/2021/02/teddyswims-vot-180x180.jpg","rank":8,"last_week_rank":8,"peak_rank":8,"weeks_on_chart":23},{"name":"Snooze","artist":"SZA","image":"https://charts-static.billboard.com/img/2022/12/sza-xyh-snooze-eom-180x180.jpg","rank":9,"last_week_rank":6,"peak_rank":2,"weeks_on_chart":57},{"name":"Nee-nah","artist":"21 Savage, Travis Scott & Metro Boomin","image":"https://charts-static.billboard.com/img/2016/08/21-savage-iy5-180x180.jpg","rank":10,"last_week_rank":null,"peak_rank":10,"weeks_on_chart":1},{"name":"Agora Hills","artist":"Doja Cat","image":"https://charts-static.billboard.com/img/2018/04/dojacat-cqv-180x180.jpg","rank":11,"last_week_rank":9,"peak_rank":9,"weeks_on_chart":17},{"name":"Water","artist":"Tyla","image":"https://charts-static.billboard.com/img/2023/09/tyla-000-water-6ao-180x180.jpg","rank":12,"last_week_rank":7,"peak_rank":7,"weeks_on_chart":16},{"name":"Last Night","artist":"Morgan Wallen","image":"https://charts-static.billboard.com/img/2016/08/morgan-wallen-dqx-180x180.jpg","rank":13,"last_week_rank":10,"peak_rank":1,"weeks_on_chart":51},{"name":"Thinkin' Bout Me","artist":"Morgan Wallen","image":"https://charts-static.billboard.com/img/2016/08/morgan-wallen-dqx-180x180.jpg","rank":14,"last_week_rank":12,"peak_rank":7,"weeks_on_chart":46},{"name":"Fast Car","artist":"Luke Combs","image":"https://charts-static.billboard.com/img/2015/07/luke-combs-9dm-180x180.jpg","rank":15,"last_week_rank":11,"peak_rank":2,"weeks_on_chart":43},{"name":"Stick Season","artist":"Noah Kahan","image":"https://charts-static.billboard.com/img/2022/07/noah-kahan-k6d-stickseason-gpe-180x180.jpg","rank":16,"last_week_rank":14,"peak_rank":14,"weeks_on_chart":16},{"name":"Is It Over Now? (Taylor's Version) [From The Vault]","artist":"Taylor Swift","image":"https://charts-static.billboard.com/img/2006/07/taylor-swift-9sy-180x180.jpg","rank":17,"last_week_rank":13,"peak_rank":1,"weeks_on_chart":12},{"name":"All Of Me","artist":"21 Savage","image":"https://charts-static.billboard.com/img/2016/08/21-savage-iy5-180x180.jpg","rank":18,"last_week_rank":null,"peak_rank":18,"weeks_on_chart":1},{"name":"N.H.I.E.","artist":"21 Savage & Doja Cat","image":"https://charts-static.billboard.com/img/2016/08/21-savage-iy5-180x180.jpg","rank":19,"last_week_rank":null,"peak_rank":19,"weeks_on_chart":1},{"name":"What Was I Made For?","artist":"Billie Eilish","image":"https://charts-static.billboard.com/img/2023/07/billie-eilish-lrt-whatwasimadeforX-kn4-180x180.jpg","rank":20,"last_week_rank":16,"peak_rank":14,"weeks_on_chart":26}]
